imgbytesizer/__init__.py
imgbytesizer/formatter.py
imgbytesizer/logger.py
imgbytesizer/main.py
imgbytesizer/py.typed
imgbytesizer/resizer.py
imgbytesizer/utils.py
imgbytesizer-0.2.5.dist-info/LICENSE
imgbytesizer-0.2.5.dist-info/METADATA
imgbytesizer-0.2.5.dist-info/WHEEL
imgbytesizer-0.2.5.dist-info/entry_points.txt
imgbytesizer-0.2.5.dist-info/RECORD
