Metadata-Version: 2.3
Name: imgbytesizer
Version: 0.2.5
Summary: A CLI tool to resize images to a target file size.
License: MIT
Keywords: image,resize,compression,cli,optimize
Author: pyyupsk
Author-email: contact@fasu.dev
Requires-Python: >=3.9
Classifier: License :: OSI Approved :: MIT License
Classifier: Programming Language :: Python :: 3
Classifier: Programming Language :: Python :: 3.9
Classifier: Programming Language :: Python :: 3.10
Classifier: Programming Language :: Python :: 3.11
Classifier: Programming Language :: Python :: 3.12
Classifier: Programming Language :: Python :: 3.13
Requires-Dist: pillow (>=11.2.1,<12.0.0)
Requires-Dist: pyfiglet (>=1.0.2,<2.0.0)
Requires-Dist: tabulate (>=0.9.0,<0.10.0)
